bioio_tifffile/__init__.py
bioio_tifffile/reader.py
bioio_tifffile/reader_metadata.py
bioio_tifffile/utils.py
bioio_tifffile/tests/__init__.py
bioio_tifffile/tests/conftest.py
bioio_tifffile/tests/test_reader.py
bioio_tifffile_fork_by_bugra-0.0.1b2.dist-info/licenses/LICENSE
scripts/TEST_RESOURCES_HASH.txt
scripts/download_test_resources.py
scripts/upload_test_resources.py
bioio_tifffile_fork_by_bugra-0.0.1b2.dist-info/METADATA
bioio_tifffile_fork_by_bugra-0.0.1b2.dist-info/WHEEL
bioio_tifffile_fork_by_bugra-0.0.1b2.dist-info/entry_points.txt
bioio_tifffile_fork_by_bugra-0.0.1b2.dist-info/top_level.txt
bioio_tifffile_fork_by_bugra-0.0.1b2.dist-info/RECORD
